{
  "swagger": "2.0",
  "info": {
    "title": "api.proto",
    "version": "version not set"
  },
  "schemes": [
    "http",
    "https"
  ],
  "consumes": [
    "application/json"
  ],
  "produces": [
    "application/json"
  ],
  "paths": {
    "/v1/customers": {
      "post": {
        "operationId": "CreateCustomer",
        "responses": {
          "200": {
            "description": "A successful response.",
            "schema": {
              "$ref": "#/definitions/apiCreateCustomerResponse"
            }
          }
        },
        "parameters": [
          {
            "name": "body",
            "in": "body",
            "required": true,
            "schema": {
              "$ref": "#/definitions/apiCreateCustomerRequest"
            }
          }
        ],
        "tags": [
          "CustomerService"
        ]
      }
    }
  },
  "definitions": {
    "apiAppMetadata": {
      "type": "object",
      "properties": {
        "plan": {
          "type": "string"
        },
        "pay_token": {
          "type": "string"
        }
      }
    },
    "apiCreateCustomerRequest": {
      "type": "object",
      "properties": {
        "user_info": {
          "$ref": "#/definitions/apiUserInfo"
        }
      }
    },
    "apiCreateCustomerResponse": {
      "type": "object",
      "properties": {
        "id": {
          "type": "string"
        }
      }
    },
    "apiUserInfo": {
      "type": "object",
      "properties": {
        "name": {
          "type": "string"
        },
        "given_name": {
          "type": "string"
        },
        "family_name": {
          "type": "string"
        },
        "gender": {
          "type": "string"
        },
        "birthdate": {
          "type": "string"
        },
        "email": {
          "type": "string"
        },
        "picture": {
          "type": "string"
        },
        "user_metadata": {
          "$ref": "#/definitions/apiUserMetadata"
        },
        "app_metadata": {
          "$ref": "#/definitions/apiAppMetadata"
        }
      }
    },
    "apiUserMetadata": {
      "type": "object",
      "properties": {
        "phone": {
          "type": "string"
        },
        "preferred_contact": {
          "type": "string"
        }
      }
    }
  }
}
